{"turns":[{"actions":[{"workerID":"P1-F","targetX":2,"targetY":0},{"workerID":"P1-M","targetX":2,"targetY":2}],"player":{"nickname":"giovanni","playerNum":1,"color":"BLUE","card":{"name":"Apollo","num":1,"description":"Your Move: Your Worker may move into an opponent Worker’s space by forcing their Worker to the space yours just vacated."},"workers":[{"sex":"FEMALE","playerId":1,"space":{"posX":2,"posY":0,"worker":{"sex":"FEMALE","playerId":1,"space":{"posX":2,"posY":0,"worker":{"sex":"FEMALE","playerId":1,"space":{"posX":2,"posY":0,"worker":{"sex":"FEMALE","playerId":1,"space":{"posX":2,"posY":0,"worker":{"sex":"FEMALE","playerId":1,"space":{"posX":2,"posY":0,"worker":{"sex":"FEMALE","playerId":1,"space":{"posX":2,"posY":0,"worker":{"sex":"FEMALE","playerId":1,"space":{"posX":2,"posY":0,"worker":{"sex":"FEMALE","playerId":1,"space":{"posX":2,"posY":0,"worker":{"sex":"FEMALE","playerId":1,"space":{"posX":2,"posY":0,"worker":{"sex":"FEMALE","playerId":1,"space":{"posX":2,"posY":0,"worker":{"sex":"FEMALE","playerId":1,"space":{"posX":2,"posY":0,"worker":{"sex":"FEMALE","playerId":1,"space":{"posX":2,"posY":0,"worker":{"sex":"FEMALE","playerId":1,"space":{"posX":2,"posY":0,"worker":{"sex":"FEMALE","playerId":1,"space":{"posX":2,"posY":0,"worker":{"sex":"FEMALE","playerId":1,"space":{"posX":2,"posY":0,"worker":{"sex":"FEMALE","playerId":1,"space":{"posX":2,"posY":0,"worker":{"sex":"FEMALE","playerId":1,"space":{"posX":2,"posY":0,"worker":{"sex":"FEMALE","playerId":1,"space":{"posX":2,"posY":0,"worker":{"sex":"FEMALE","playerId":1,"space":{"posX":2,"posY":0,"worker":{"sex":"FEMALE","playerId":1,"space":{"posX":2,"posY":0,"worker":{"sex":"FEMALE","playerId":1,"space":{"posX":2,"posY":0,"worker":{"sex":"FEMALE","playerId":1,"space":{"posX":2,"posY":0,"worker":{"sex":"FEMALE","playerId":1,"space":{"posX":2,"posY":0,"worker":{"sex":"FEMALE","playerId":1,"space":{"posX":2,"posY":0,"worker":{"sex":"FEMALE","playerId":1,"space":{"posX":2,"posY":0,"worker":{"sex":"FEMALE","playerId":1,"space":{"posX":2,"posY":0,"worker":{"sex":"FEMALE","playerId":1,"space":{"posX":2,"posY":0,"worker":{"sex":"FEMALE","playerId":1,"space":{"posX":2,"posY":0,"worker":{"sex":"FEMALE","playerId":1,"space":{"posX":2,"posY":0,"worker":{"sex":"FEMALE","playerId":1,"space":{"posX":2,"posY":0,"worker":{"sex":"FEMALE","playerId":1,"space":{"posX":2,"posY":0,"worker":{"sex":"FEMALE","playerId":1,"space":{"posX":2,"posY":0,"worker":{"sex":"FEMALE","playerId":1,"space":{"posX":2,"posY":0,"worker":{"sex":"FEMALE","playerId":1,"space":{"posX":2,"posY":0,"worker":{"sex":"FEMALE","playerId":1,"space":{"posX":2,"posY":0,"worker":{"sex":"FEMALE","playerId":1,"space":{"posX":2,"posY":0,"worker":{"sex":"FEMALE","playerId":1,"space":{"posX":2,"posY":0,"worker":{"sex":"FEMALE","playerId":1,"space":{"posX":2,"posY":0,"worker":{"sex":"FEMALE","playerId":1,"space":{"posX":2,"posY":0,"worker":{"sex":"FEMALE","playerId":1,"space":{"posX":2,"posY":0,"worker":{"sex":"FEMALE","playerId":1,"space":{"posX":2,"posY":0,"worker":{"sex":"FEMALE","playerId":1,"space":{"posX":2,"posY":0,"worker":{"sex":"FEMALE","playerId":1,"space":{"posX":2,"posY":0,"worker":{"sex":"FEMALE","playerId":1,"space":{"posX":2,"posY":0,"worker":{"sex":"FEMALE","playerId":1,"space":{"posX":2,"posY":0,"worker":{"sex":"FEMALE","playerId":1,"space":{"posX":2,"posY":0,"worker":{"sex":"FEMALE","playerId":1,"space":{"posX":2,"posY":0,"worker":{"sex":"FEMALE","playerId":1,"space":{"posX":2,"posY":0,"worker":{"sex":"FEMALE","playerId":1,"space":{"posX":2,"posY":0,"worker":{"sex":"FEMALE","playerId":1,"space":{"posX":2,"posY":0,"worker":{"sex":"FEMALE","playerId":1,"space":{"posX":2,"posY":0,"worker":{"sex":"FEMALE","playerId":1,"space":{"posX":2,"posY":0,"worker":{"sex":"FEMALE","playerId":1,"space":{"posX":2,"posY":0,"worker":{"sex":"FEMALE","playerId":1,"space":{"posX":2,"posY":0,"worker":{"sex":"FEMALE","playerId":1,"space":{"posX":2,"posY":0,"worker":{"sex":"FEMALE","playerId":1,"space":{"posX":2,"posY":0,"worker":{"sex":"FEMALE","playerId":1,"space":{"posX":2,"posY":0,"worker":{"sex":"FEMALE","playerId":1,"space":{"posX":2,"posY":0,"worker":{"sex":"FEMALE","playerId":1,"space":{"posX":2,"posY":0,"worker":{"sex":"FEMALE","playerId":1,"space":{"posX":2,"posY":0,"worker":{"sex":"FEMALE","playerId":1,"space":{"posX":2,"posY":0,"worker":{"sex":"FEMALE","playerId":1,"space":{"posX":2,"posY":0,"worker":{"sex":"FEMALE","playerId":1,"space":{"posX":2,"posY":0,"worker":{"sex":"FEMALE","playerId":1,"space":{"posX":2,"posY":0,"worker":{"sex":"FEMALE","playerId":1,"space":{"posX":2,"posY":0,"worker":{"sex":"FEMALE","playerId":1,"space":{"posX":2,"posY":0,"worker":{"sex":"FEMALE","playerId":1,"space":{"posX":2,"posY":0,"worker":{"sex":"FEMALE","playerId":1,"space":{"posX":2,"posY":0,"worker":{"sex":"FEMALE","playerId":1,"space":{"posX":2,"posY":0,"worker":{"sex":"FEMALE","playerId":1,"space":{"posX":2,"posY":0,"worker":{"sex":"FEMALE","playerId":1,"space":{"posX":2,"posY":0,"worker":{"sex":"FEMALE","playerId":1,"space":{"posX":2,"posY":0,"worker":{"sex":"FEMALE","playerId":1,"space":{"posX":2,"posY":0,"worker":{"sex":"FEMALE","playerId":1,"space":{"posX":2,"posY":0,"worker":{"sex":"FEMALE","playerId":1,"space":{"posX":2,"posY":0,"worker":{"sex":"FEMALE","playerId":1,"space":{"posX":2,"posY":0,"worker":{"sex":"FEMALE","playerId":1,"space":{"posX":2,"posY":0,"worker":{"sex":"FEMALE","playerId":1,"space":{"posX":2,"posY":0,"worker":{"sex":"FEMALE","playerId":1,"space":{"posX":2,"posY":0,"worker":{"sex":"FEMALE","playerId":1,"space":{"posX":2,"posY":0,"worker":{"sex":"FEMALE","playerId":1,"space":{"posX":2,"posY":0,"worker":{"sex":"FEMALE","playerId":1,"space":{"posX":2,"posY":0,"worker":{"sex":"FEMALE","playerId":1,"space":{"posX":2,"posY":0,"worker":{"sex":"FEMALE","playerId":1,"space":{"posX":2,"posY":0,"worker":{"sex":"FEMALE","playerId":1,"space":{"posX":2,"posY":0,"worker":{"sex":"FEMALE","playerId":1,"space":{"posX":2,"posY":0,"worker":{"sex":"FEMALE","playerId":1,"space":{"posX":2,"posY":0,"worker":{"sex":"FEMALE","playerId":1,"space":{"posX":2,"posY":0,"worker":{"sex":"FEMALE","playerId":1,"space":{"posX":2,"posY":0,"worker":{"sex":"FEMALE","playerId":1,"space":{"posX":2,"posY":0,"worker":{"sex":"FEMALE","playerId":1,"space":{"posX":2,"posY":0,"worker":{"sex":"FEMALE","playerId":1,"space":{"posX":2,"posY":0,"worker":{"sex":"FEMALE","playerId":1,"space":{"posX":2,"posY":0,"worker":{"sex":"FEMALE","playerId":1,"space":{"posX":2,"posY":0,"worker":{"sex":"FEMALE","playerId":1,"space":{"posX":2,"posY":0,"worker":{"sex":"FEMALE","playerId":1,"space":{"posX":2,"posY":0,"worker":{"sex":"FEMALE","playerId":1,"space":{"posX":2,"posY":0,"worker":{"sex":"FEMALE","playerId":1,"space":{"posX":2,"posY":0,"worker":{"sex":"FEMALE","playerId":1,"space":{"posX":2,"posY":0,"worker":{"sex":"FEMALE","playerId":1,"space":{"posX":2,"posY":0,"worker":{"sex":"FEMALE","playerId":1,"space":{"posX":2,"posY":0,"worker":{"sex":"FEMALE","playerId":1,"space":{"posX":2,"posY":0,"worker":{"sex":"FEMALE","playerId":1,"space":{"posX":2,"posY":0,"worker":{"sex":"FEMALE","playerId":1,"space":{"posX":2,"posY":0,"worker":{"sex":"FEMALE","playerId":1,"space":{"posX":2,"posY":0,"worker":{"sex":"FEMALE","playerId":1,"space":{"posX":2,"posY":0,"worker":{"sex":"FEMALE","playerId":1,"space":{"posX":2,"posY":0,"worker":{"sex":"FEMALE","playerId":1,"space":{"posX":2,"posY":0,"worker":{"sex":"FEMALE","playerId":1,"space":{"posX":2,"posY":0,"worker":{"sex":"FEMALE","playerId":1,"space":{"posX":2,"posY":0,"worker":{"sex":"FEMALE","playerId":1,"space":{"posX":2,"posY":0,"worker":{"sex":"FEMALE","playerId":1,"space":{"posX":2,"posY":0,"worker":{"sex":"FEMALE","playerId":1,"space":{"posX":2,"posY":0,"worker":{"sex":"FEMALE","playerId":1,"space":{"posX":2,"posY":0,"worker":{"sex":"FEMALE","playerId":1,"space":{"posX":2,"posY":0,"worker":{"sex":"FEMALE","playerId":1,"space":{"posX":2,"posY":0,"worker":{"sex":"FEMALE","playerId":1,"space":{"posX":2,"posY":0,"worker":{"sex":"FEMALE","playerId":1,"space":{"posX":2,"posY":0,"worker":{"sex":"FEMALE","playerId":1,"space":{"posX":2,"posY":0,"worker":{"sex":"FEMALE","playerId":1,"space":{"posX":2,"posY":0,"worker":{"sex":"FEMALE","playerId":1,"space":{"posX":2,"posY":0,"worker":{"sex":"FEMALE","playerId":1,"space":{"posX":2,"posY":0,"worker":{"sex":"FEMALE","playerId":1,"space":{"posX":2,"posY":0,"worker":{"sex":"FEMALE","playerId":1,"space":{"posX":2,"posY":0,"worker":{"sex":"FEMALE","playerId":1,"space":{"posX":2,"posY":0,"worker":{"sex":"FEMALE","playerId":1,"space":{"posX":2,"posY":0,"worker":{"sex":"FEMALE","playerId":1,"space":{"posX":2,"posY":0,"worker":{"sex":"FEMALE","playerId":1,"space":{"posX":2,"posY":0,"worker":{"sex":"FEMALE","playerId":1,"space":{"posX":2,"posY":0,"worker":{"sex":"FEMALE","playerId":1,"space":{"posX":2,"posY":0,"worker":{"sex":"FEMALE","playerId":1,"space":{"posX":2,"posY":0,"worker":{"sex":"FEMALE","playerId":1,"space":{"posX":2,"posY":0,"worker":{"sex":"FEMALE","playerId":1,"space":{"posX":2,"posY":0,"worker":{"sex":"FEMALE","playerId":1,"space":{"posX":2,"posY":0,"worker":{"sex":"FEMALE","playerId":1,"space":{"posX":2,"posY":0,"worker":{"sex":"FEMALE","playerId":1,"space":{"posX":2,"posY":0,"worker":{"sex":"FEMALE","playerId":1,"space":{"posX":2,"posY":0,"worker":{"sex":"FEMALE","playerId":1,"space":{"posX":2,"posY":0,"worker":{"sex":"FEMALE","playerId":1,"space":{"posX":2,"posY":0,"worker":{"sex":"FEMALE","playerId":1,"space":{"posX":2,"posY":0,"worker":{"sex":"FEMALE","playerId":1,"space":{"posX":2,"posY":0,"worker":{"sex":"FEMALE","playerId":1,"space":{"posX":2,"posY":0,"worker":{"sex":"FEMALE","playerId":1,"space":{"posX":2,"posY":0,"worker":{"sex":"FEMALE","playerId":1,"space":{"posX":2,"posY":0,"worker":{"sex":"FEMALE","playerId":1,"space":{"posX":2,"posY":0,"worker":{"sex":"FEMALE","playerId":1,"space":{"posX":2,"posY":0,"worker":{"sex":"FEMALE","playerId":1,"space":{"posX":2,"posY":0,"worker":{"sex":"FEMALE","playerId":1,"space":{"posX":2,"posY":0,"worker":{"sex":"FEMALE","playerId":1,"space":{"posX":2,"posY":0,"worker":{"sex":"FEMALE","playerId":1,"space":{"posX":2,"posY":0,"worker":{"sex":"FEMALE","playerId":1,"space":{"posX":2,"posY":0,"worker":{"sex":"FEMALE","playerId":1,"space":{"posX":2,"posY":0,"worker":{"sex":"FEMALE","playerId":1,"space":{"posX":2,"posY":0,"worker":{"sex":"FEMALE","playerId":1,"space":{"posX":2,"posY":0,"worker":{"sex":"FEMALE","playerId":1,"space":{"posX":2,"posY":0,"worker":{"sex":"FEMALE","playerId":1,"space":{"posX":2,"posY":0,"worker":{"sex":"FEMALE","playerId":1,"space":{"posX":2,"posY":0,"worker":{"sex":"FEMALE","playerId":1,"space":{"posX":2,"posY":0,"worker":{"sex":"FEMALE","playerId":1,"space":{"posX":2,"posY":0,"worker":{"sex":"FEMALE","playerId":1,"space":{"posX":2,"posY":0,"worker":{"sex":"FEMALE","playerId":1,"space":{"posX":2,"posY":0,"worker":{"sex":"FEMALE","playerId":1,"space":{"posX":2,"posY":0,"worker":{"sex":"FEMALE","playerId":1,"space":{"posX":2,"posY":0,"worker":{"sex":"FEMALE","playerId":1,"space":{"posX":2,"posY":0,"worker":{"sex":"FEMALE","playerId":1,"space":{"posX":2,"posY":0,"worker":{"sex":"FEMALE","playerId":1,"space":{"posX":2,"posY":0,"worker":{"sex":"FEMALE","playerId":1,"space":{"posX":2,"posY":0,"worker":{"sex":"FEMALE","playerId":1,"space":{"posX":2,"posY":0,"worker":{"sex":"FEMALE","playerId":1,"space":{"posX":2,"posY":0,"worker":{"sex":"FEMALE","playerId":1,"space":{"posX":2,"posY":0,"worker":{"sex":"FEMALE","playerId":1,"space":{"posX":2,"posY":0,"worker":{"sex":"FEMALE","playerId":1,"space":{"posX":2,"posY":0,"worker":{"sex":"FEMALE","playerId":1,"space":{"posX":2,"posY":0,"worker":{"sex":"FEMALE","playerId":1,"space":{"posX":2,"posY":0,"worker":{"sex":"FEMALE","playerId":1,"space":{"posX":2,"posY":0,"worker":{"sex":"FEMALE","playerId":1,"space":{"posX":2,"posY":0,"worker":{"sex":"FEMALE","playerId":1,"space":{"posX":2,"posY":0,"worker":{"sex":"FEMALE","playerId":1,"space":{"posX":2,"posY":0,"worker":{"sex":"FEMALE","playerId":1,"space":{"posX":2,"posY":0,"worker":{"sex":"FEMALE","playerId":1,"space":{"posX":2,"posY":0,"worker":{"sex":"FEMALE","playerId":1,"space":{"posX":2,"posY":0,"worker":{"sex":"FEMALE","playerId":1,"space":{"posX":2,"posY":0,"worker":{"sex":"FEMALE","playerId":1,"space":{"posX":2,"posY":0,"worker":{"sex":"FEMALE","playerId":1,"space":{"posX":2,"posY":0,"worker":{"sex":"FEMALE","playerId":1,"space":{"posX":2,"posY":0,"worker":{"sex":"FEMALE","playerId":1,"space":{"posX":2,"posY":0,"worker":{"sex":"FEMALE","playerId":1,"space":{"posX":2,"posY":0,"worker":{"sex":"FEMALE","playerId":1,"space":{"posX":2,"posY":0,"worker":{"sex":"FEMALE","playerId":1,"space":{"posX":2,"posY":0,"worker":{"sex":"FEMALE","playerId":1,"space":{"posX":2,"posY":0,"worker":{"sex":"FEMALE","playerId":1,"space":{"posX":2,"posY":0,"worker":{"sex":"FEMALE","playerId":1,"space":{"posX":2,"posY":0,"worker":{"sex":"FEMALE","playerId":1,"space":{"posX":2,"posY":0,"worker":{"sex":"FEMALE","playerId":1,"space":{"posX":2,"posY":0,"worker":{"sex":"FEMALE","playerId":1,"space":{"posX":2,"posY":0,"worker":{"sex":"FEMALE","playerId":1,"space":{"posX":2,"posY":0,"worker":{"sex":"FEMALE","playerId":1,"space":{"posX":2,"posY":0,"worker":{"sex":"FEMALE","playerId":1,"space":{"posX":2,"posY":0,"worker":{"sex":"FEMALE","playerId":1,"space":{"posX":2,"posY":0,"worker":{"sex":"FEMALE","playerId":1,"space":{"posX":2,"posY":0,"worker":{"sex":"FEMALE","playerId":1,"space":{"posX":2,"posY":0,"worker":{"sex":"FEMALE","playerId":1,"space":{"posX":2,"posY":0,"worker":{"sex":"FEMALE","playerId":1,"space":{"posX":2,"posY":0,"worker":{"sex":"FEMALE","playerId":1,"space":{"posX":2,"posY":0,"worker":{"sex":"FEMALE","playerId":1,"space":{"posX":2,"posY":0,"worker":{"sex":"FEMALE","playerId":1,"space":{"posX":2,"posY":0,"worker":{"sex":"FEMALE","playerId":1,"space":{"posX":2,"posY":0,"worker":{"sex":"FEMALE","playerId":1,"space":{"posX":2,"posY":0,"worker":{"sex":"FEMALE","playerId":1,"space":{"posX":2,"posY":0,"worker":{"sex":"FEMALE","playerId":1,"space":{"posX":2,"posY":0,"worker":{"sex":"FEMALE","playerId":1,"space":{"posX":2,"posY":0,"worker":{"sex":"FEMALE","playerId":1,"space":{"posX":2,"posY":0,"worker":{"sex":"FEMALE","playerId":1,"space":{"posX":2,"posY":0,"worker":{"sex":"FEMALE","playerId":1,"space":{"posX":2,"posY":0,"worker":{"sex":"FEMALE","playerId":1,"space":{"posX":2,"posY":0,"worker":{"sex":"FEMALE","playerId":1,"space":{"posX":2,"posY":0,"worker":{"sex":"FEMALE","playerId":1,"space":{"posX":2,"posY":0,"worker":{"sex":"FEMALE","playerId":1,"space":{"posX":2,"posY":0,"worker":{"sex":"FEMALE","playerId":1,"space":{"posX":2,"posY":0,"worker":{"sex":"FEMALE","playerId":1,"space":{"posX":2,"posY":0,"worker":{"sex":"FEMALE","playerId":1,"space":{"posX":2,"posY":0,"worker":{"sex":"FEMALE","playerId":1,"space":{"posX":2,"posY":0,"worker":{"sex":"FEMALE","playerId":1,"space":{"posX":2,"posY":0,"worker":{"sex":"FEMALE","playerId":1,"space":{"posX":2,"posY":0,"worker":{"sex":"FEMALE","playerId":1,"space":{"posX":2,"posY":0,"worker":{"sex":"FEMALE","playerId":1,"space":{"posX":2,"posY":0,"worker":{"sex":"FEMALE","playerId":1,"space":{"posX":2,"posY":0,"worker":{"sex":"FEMALE","playerId":1,"space":{"posX":2,"posY":0,"worker":{"sex":"FEMALE","playerId":1,"space":{"posX":2,"posY":0,"worker":{"sex":"FEMALE","playerId":1,"space":{"posX":2,"posY":0,"worker":{"sex":"FEMALE","playerId":1,"space":{"posX":2,"posY":0,"worker":{"sex":"FEMALE","playerId":1,"space":{"posX":2,"posY":0,"worker":{"sex":"FEMALE","playerId":1,"space":{"posX":2,"posY":0,"worker":{"sex":"FEMALE","playerId":1,"space":{"posX":2,"posY":0,"worker":{"sex":"FEMALE","playerId":1,"space":{"posX":2,"posY":0,"worker":{"sex":"FEMALE","playerId":1,"space":{"posX":2,"posY":0,"worker":{"sex":"FEMALE","playerId":1,"space":{"posX":2,"posY":0,"worker":{"sex":"FEMALE","playerId":1,"space":{"posX":2,"posY":0,"worker":{"sex":"FEMALE","playerId":1,"space":{"posX":2,"posY":0,"worker":{"sex":"FEMALE","playerId":1,"space":{"posX":2,"posY":0,"worker":{"sex":"FEMALE","playerId":1,"space":{"posX":2,"posY":0,"worker":{"sex":"FEMALE","playerId":1,"space":{"posX":2,"posY":0,"worker":{"sex":"FEMALE","playerId":1,"space":{"posX":2,"posY":0,"worker":{"sex":"FEMALE","playerId":1,"space":{"posX":2,"posY":0,"worker":{"sex":"FEMALE","playerId":1,"space":{"posX":2,"posY":0,"worker":{"sex":"FEMALE","playerId":1,"space":{"posX":2,"posY":0,"worker":{"sex":"FEMALE","playerId":1,"space":{"posX":2,"posY":0,"worker":{"sex":"FEMALE","playerId":1,"space":{"posX":2,"posY":0,"worker":{"sex":"FEMALE","playerId":1,"space":{"posX":2,"posY":0,"worker":{"sex":"FEMALE","playerId":1,"space":{"posX":2,"posY":0,"worker":{"sex":"FEMALE","playerId":1,"space":{"posX":2,"posY":0,"worker":{"sex":"FEMALE","playerId":1,"space":{"posX":2,"posY":0,"worker":{"sex":"FEMALE","playerId":1,"space":{"posX":2,"posY":0,"worker":{"sex":"FEMALE","playerId":1,"space":{"posX":2,"posY":0,"worker":{"sex":"FEMALE","playerId":1,"space":{"posX":2,"posY":0,"worker":{"sex":"FEMALE","playerId":1,"space":{"posX":2,"posY":0,"worker":{"sex":"FEMALE","playerId":1,"space":{"posX":2,"posY":0,"worker":{"sex":"FEMALE","playerId":1,"space":{"posX":2,"posY":0,"worker":{"sex":"FEMALE","playerId":1,"space":{"posX":2,"posY":0,"worker":{"sex":"FEMALE","playerId":1,"space":{"posX":2,"posY":0,"worker":{"sex":"FEMALE","playerId":1,"space":{"posX":2,"posY":0,"worker":{"sex":"FEMALE","playerId":1,"space":{"posX":2,"posY":0,"worker":{"sex":"FEMALE","playerId":1,"space":{"posX":2,"posY":0,"worker":{"sex":"FEMALE","playerId":1,"space":{"posX":2,"posY":0,"worker":{"sex":"FEMALE","playerId":1,"space":{"posX":2,"posY":0,"worker":{"sex":"FEMALE","playerId":1,"space":{"posX":2,"posY":0,"worker":{"sex":"FEMALE","playerId":1,"space":{"posX":2,"posY":0,"worker":{"sex":"FEMALE","playerId":1,"space":{"posX":2,"posY":0,"worker":{"sex":"FEMALE","playerId":1,"space":{"posX":2,"posY":0,"worker":{"sex":"FEMALE","playerId":1,"space":{"posX":2,"posY":0,"worker":{"sex":"FEMALE","playerId":1,"space":{"posX":2,"posY":0,"worker":{"sex":"FEMALE","playerId":1,"space":{"posX":2,"posY":0,"worker":{"sex":"FEMALE","playerId":1,"space":{"posX":2,"posY":0,"worker":{"sex":"FEMALE","playerId":1,"space":{"posX":2,"posY":0,"worker":{"sex":"FEMALE","playerId":1,"space":{"posX":2,"posY":0,"worker":{"sex":"FEMALE","playerId":1,"space":{"posX":2,"posY":0,"worker":{"sex":"FEMALE","playerId":1,"space":{"posX":2,"posY":0,"worker":{"sex":"FEMALE","playerId":1,"space":{"posX":2,"posY":0,"worker":{"sex":"FEMALE","playerId":1,"space":{"posX":2,"posY":0,"worker":{"sex":"FEMALE","playerId":1,"space":{"posX":2,"posY":0,"worker":{"sex":"FEMALE","playerId":1,"space":{"posX":2,"posY":0,"worker":{"sex":"FEMALE","playerId":1,"space":{"posX":2,"posY":0,"worker":{"sex":"FEMALE","playerId":1,"space":{"posX":2,"posY":0,"worker":{"sex":"FEMALE","playerId":1,"space":{"posX":2,"posY":0,"worker":{"sex":"FEMALE","playerId":1,"space":{"posX":2,"posY":0,"worker":{"sex":"FEMALE","playerId":1,"space":{"posX":2,"posY":0,"worker":{"sex":"FEMALE","playerId":1,"space":{"posX":2,"posY":0,"worker":{"sex":"FEMALE","playerId":1,"space":{"posX":2,"posY":0,"worker":{"sex":"FEMALE","playerId":1,"space":{"posX":2,"posY":0,"worker":{"sex":"FEMALE","playerId":1,"space":{"posX":2,"posY":0,"worker":{"sex":"FEMALE","playerId":1,"space":{"posX":2,"posY":0,"worker":{"sex":"FEMALE","playerId":1,"space":{"posX":2,"posY":0,"worker":{"sex":"FEMALE","playerId":1,"space":{"posX":2,"posY":0,"worker":{"sex":"FEMALE","playerId":1,"space":{"posX":2,"posY":0,"worker":{"sex":"FEMALE","playerId":1,"space":{"posX":2,"posY":0,"worker":{"sex":"FEMALE","playerId":1,"space":{"posX":2,"posY":0,"worker":{"sex":"FEMALE","playerId":1,"space":{"posX":2,"posY":0,"worker":{"sex":"FEMALE","playerId":1,"space":{"posX":2,"posY":0,"worker":{"sex":"FEMALE","playerId":1,"space":{"posX":2,"posY":0,"worker":{"sex":"FEMALE","playerId":1,"space":{"posX":2,"posY":0,"worker":{"sex":"FEMALE","playerId":1,"space":{"posX":2,"posY":0,"worker":{"sex":"FEMALE","playerId":1,"space":{"posX":2,"posY":0,"worker":{"sex":"FEMALE","playerId":1,"space":{"posX":2,"posY":0,"worker":{"sex":"FEMALE","playerId":1,"space":{"posX":2,"posY":0,"worker":{"sex":"FEMALE","playerId":1,"space":{"posX":2,"posY":0,"worker":{"sex":"FEMALE","playerId":1,"space":{"posX":2,"posY":0,"worker":{"sex":"FEMALE","playerId":1,"space":{"posX":2,"posY":0,"worker":{"sex":"FEMALE","playerId":1,"space":{"posX":2,"posY":0,"worker":{"sex":"FEMALE","playerId":1,"space":{"posX":2,"posY":0,"worker":{"sex":"FEMALE","playerId":1,"space":{"posX":2,"posY":0,"worker":{"sex":"FEMALE","playerId":1,"space":{"posX":2,"posY":0,"worker":{"sex":"FEMALE","playerId":1,"space":{"posX":2,"posY":0,"worker":{"sex":"FEMALE","playerId":1,"space":{"posX":2,"posY":0,"worker":{"sex":"FEMALE","playerId":1,"space":{"posX":2,"posY":0,"worker":{"sex":"FEMALE","playerId":1,"space":{"posX":2,"posY":0,"worker":{"sex":"FEMALE","playerId":1,"space":{"posX":2,"posY":0,"worker":{"sex":"FEMALE","playerId":1,"space":{"posX":2,"posY":0,"worker":{"sex":"FEMALE","playerId":1,"space":{"posX":2,"posY":0,"worker":{"sex":"FEMALE","playerId":1,"space":{"posX":2,"posY":0,"worker":{"sex":"FEMALE","playerId":1,"space":{"posX":2,"posY":0,"worker":{"sex":"FEMALE","playerId":1,"space":{"posX":2,"posY":0,"worker":{"sex":"FEMALE","playerId":1,"space":{"posX":2,"posY":0,"worker":{"sex":"FEMALE","playerId":1,"space":{"posX":2,"posY":0,"worker":{"sex":"FEMALE","playerId":1,"space":{"posX":2,"posY":0,"worker":{"sex":"FEMALE","playerId":1,"space":{"posX":2,"posY":0,"worker":{"sex":"FEMALE","playerId":1,"space":{"posX":2,"posY":0,"worker":{"sex":"FEMALE","playerId":1,"space":{"posX":2,"posY":0,"worker":{"sex":"FEMALE","playerId":1,"space":{"posX":2,"posY":0,"worker":{"sex":"FEMALE","playerId":1,"space":{"posX":2,"posY":0,"worker":{"sex":"FEMALE","playerId":1,"space":{"posX":2,"posY":0,"worker":{"sex":"FEMALE","playerId":1,"space":{"posX":2,"posY":0,"worker":{"sex":"FEMALE","playerId":1,"space":{"posX":2,"posY":0,"worker":{"sex":"FEMALE","playerId":1,"space":{"posX":2,"posY":0,"worker":{"sex":"FEMALE","playerId":1,"space":{"posX":2,"posY":0,"worker":{"sex":"FEMALE","playerId":1,"space":{"posX":2,"posY":0,"worker":{"sex":"FEMALE","playerId":1,"space":{"posX":2,"posY":0,"worker":{"sex":"FEMALE","playerId":1,"space":{"posX":2,"posY":0,"worker":{"sex":"FEMALE","playerId":1,"space":{"posX":2,"posY":0,"worker":{"sex":"FEMALE","playerId":1,"space":{"posX":2,"posY":0,"worker":{"sex":"FEMALE","playerId":1,"space":{"posX":2,"posY":0,"worker":{"sex":"FEMALE","playerId":1,"space":{"posX":2,"posY":0,"worker":{"sex":"FEMALE","playerId":1,"space":{"posX":2,"posY":0,"worker":{"sex":"FEMALE","playerId":1,"space":{"posX":2,"posY":0,"worker":{"sex":"FEMALE","playerId":1,"space":{"posX":2,"posY":0,"worker":{"sex":"FEMALE","playerId":1,"space":{"posX":2,"posY":0,"worker":{"sex":"FEMALE","playerId":1,"space":{"posX":2,"posY":0,"worker":{"sex":"FEMALE","playerId":1,"space":{"posX":2,"posY":0,"worker":{"sex":"FEMALE","playerId":1,"space":{"posX":2,"posY":0,"worker":{"sex":"FEMALE","playerId":1,"space":{"posX":2,"posY":0,"worker":{"sex":"FEMALE","playerId":1,"space":{"posX":2,"posY":0,"worker":{"sex":"FEMALE","playerId":1,"space":{"posX":2,"posY":0,"worker":{"sex":"FEMALE","playerId":1,"space":{"posX":2,"posY":0,"worker":{"sex":"FEMALE","playerId":1,"space":{"posX":2,"posY":0,"worker":{"sex":"FEMALE","playerId":1,"space":{"posX":2,"posY":0,"worker":{"sex":"FEMALE","playerId":1,"space":{"posX":2,"posY":0,"worker":{"sex":"FEMALE","playerId":1,"space":{"posX":2,"posY":0,"worker":{"sex":"FEMALE","playerId":1,"space":{"posX":2,"posY":0,"worker":{"sex":"FEMALE","playerId":1,"space":{"posX":2,"posY":0,"worker":{"sex":"FEMALE","playerId":1,"space":{"posX":2,"posY":0,"worker":{"sex":"FEMALE","playerId":1,"space":{"posX":2,"posY":0,"worker":{"sex":"FEMALE","playerId":1,"space":{"posX":2,"posY":0,"worker":{"sex":"FEMALE","playerId":1,"space":{"posX":2,"posY":0,"worker":{"sex":"FEMALE","playerId":1,"space":{"posX":2,"posY":0,"worker":{"sex":"FEMALE","playerId":1,"space":{"posX":2,"posY":0,"worker":{"sex":"FEMALE","playerId":1,"space":{"posX":2,"posY":0,"worker":{"sex":"FEMALE","playerId":1,"space":{"posX":2,"posY":0,"worker":{"sex":"FEMALE","playerId":1,"space":{"posX":2,"posY":0,"worker":{"sex":"FEMALE","playerId":1,"space":{"posX":2,"posY":0,"worker":{"sex":"FEMALE","playerId":1,"space":{"posX":2,"posY":0,"worker":{"sex":"FEMALE","playerId":1,"space":{"posX":2,"posY":0,"worker":{"sex":"FEMALE","playerId":1,"space":{"posX":2,"posY":0,"worker":{"sex":"FEMALE","playerId":1,"space":{"posX":2,"posY":0,"worker":{"sex":"FEMALE","playerId":1,"space":{"posX":2,"posY":0,"worker":{"sex":"FEMALE","playerId":1,"space":{"posX":2,"posY":0,"worker":{"sex":"FEMALE","playerId":1,"space":{"posX":2,"posY":0,"worker":{"sex":"FEMALE","playerId":1,"space":{"posX":2,"posY":0,"worker":{"sex":"FEMALE","playerId":1,"space":{"posX":2,"posY":0,"worker":{"sex":"FEMALE","playerId":1,"space":{"posX":2,"posY":0,"worker":{"sex":"FEMALE","playerId":1,"space":{"posX":2,"posY":0,"worker":{"sex":"FEMALE","playerId":1,"space":{"posX":2,"posY":0,"worker":{"sex":"FEMALE","playerId":1,"space":{"posX":2,"posY":0,"worker":{"sex":"FEMALE","playerId":1,"space":{"posX":2,"posY":0,"worker":{"sex":"FEMALE","playerId":1,"space":{"posX":2,"posY":0,"worker":{"sex":"FEMALE","playerId":1,"space":{"posX":2,"posY":0,"worker":{"sex":"FEMALE","playerId":1,"space":{"posX":2,"posY":0,"worker":{"sex":"FEMALE","playerId":1,"space":{"posX":2,"posY":0,"worker":{"sex":"FEMALE","playerId":1,"space":{"posX":2,"posY":0,"worker":{"sex":"FEMALE","playerId":1,"space":{"posX":2,"posY":0,"worker":{"sex":"FEMALE","playerId":1,"space":{"posX":2,"posY":0,"worker":{"sex":"FEMALE","playerId":1,"space":{"posX":2,"posY":0,"worker":{"sex":"FEMALE","playerId":1,"space":{"posX":2,"posY":0,"worker":{"sex":"FEMALE","playerId":1,"space":{"posX":2,"posY":0,"worker":{"sex":"FEMALE","playerId":1,"space":{"posX":2,"posY":0,"worker":{"sex":"FEMALE","playerId":1,"space":{"posX":2,"posY":0,"worker":{"sex":"FEMALE","playerId":1,"space":{"posX":2,"posY":0,"worker":{"sex":"FEMALE","playerId":1,"space":{"posX":2,"posY":0,"worker":{"sex":"FEMALE","playerId":1,"space":{"posX":2,"posY":0,"worker":{"sex":"FEMALE","playerId":1,"space":{"posX":2,"posY":0,"worker":{"sex":"FEMALE","playerId":1,"space":{"posX":2,"posY":0,"worker":{"sex":"FEMALE","playerId":1,"space":{"posX":2,"posY":0,"worker":{"sex":"FEMALE","playerId":1,"space":{"posX":2,"posY":0,"worker":{"sex":"FEMALE","playerId":1,"space":{"posX":2,"posY":0,"worker":{"sex":"FEMALE","playerId":1,"space":{"posX":2,"posY":0,"worker":{"sex":"FEMALE","playerId":1,"space":{"posX":2,"posY":0,"worker":{"sex":"FEMALE","playerId":1,"space":{"posX":2,"posY":0,"worker":{"sex":"FEMALE","playerId":1,"space":{"posX":2,"posY":0,"worker":{"sex":"FEMALE","playerId":1,"space":{"posX":2,"posY":0,"worker":{"sex":"FEMALE","playerId":1,"space":{"posX":2,"posY":0,"worker":{"sex":"FEMALE","playerId":1,"space":{"posX":2,"posY":0,"worker":{"sex":"FEMALE","playerId":1,"space":{"posX":2,"posY":0,"worker":{"sex":"FEMALE","playerId":1,"space":{"posX":2,"posY":0,"worker":{"sex":"FEMALE","playerId":1,"space":{"posX":2,"posY":0,"worker":{"sex":"FEMALE","playerId":1,"space":{"posX":2,"posY":0,"worker":{"sex":"FEMALE","playerId":1,"space":{"posX":2,"posY":0,"worker":{"sex":"FEMALE","playerId":1,"space":{"posX":2,"posY":0,"worker":{"sex":"FEMALE","playerId":1,"space":{"posX":2,"posY":0,"worker":{"sex":"FEMALE","playerId":1,"space":{"posX":2,"posY":0,"worker":{"sex":"FEMALE","playerId":1,"space":{"posX":2,"posY":0,"worker":{"sex":"FEMALE","playerId":1,"space":{"posX":2,"posY":0,"worker":{"sex":"FEMALE","playerId":1,"space":{"posX":2,"posY":0,"worker":{"sex":"FEMALE","playerId":1,"space":{"posX":2,"posY":0,"worker":{"sex":"FEMALE","playerId":1,"space":{"posX":2,"posY":0,"worker":{"sex":"FEMALE","playerId":1,"space":{"posX":2,"posY":0,"worker":{"sex":"FEMALE","playerId":1,"space":{"posX":2,"posY":0,"worker":{"sex":"FEMALE","playerId":1,"space":{"posX":2,"posY":0,"worker":{"sex":"FEMALE","playerId":1,"space":{"posX":2,"posY":0,"worker":{"sex":"FEMALE","playerId":1,"space":{"posX":2,"posY":0,"worker":{"sex":"FEMALE","playerId":1,"space":{"posX":2,"posY":0,"worker":{"sex":"FEMALE","playerId":1,"space":{"posX":2,"posY":0,"worker":{"sex":"FEMALE","playerId":1,"space":{"posX":2,"posY":0,"worker":{"sex":"FEMALE","playerId":1,"space":{"posX":2,"posY":0,"worker":{"sex":"FEMALE","playerId":1,"space":{"posX":2,"posY":0,"worker":{"sex":"FEMALE","playerId":1,"space":{"posX":2,"posY":0,"worker":{"sex":"FEMALE","playerId":1,"space":{"posX":2,"posY":0,"worker":{"sex":"FEMALE","playerId":1,"space":{"posX":2,"posY":0,"worker":{"sex":"FEMALE","playerId":1,"space":{"posX":2,"posY":0,"worker":{"sex":"FEMALE","playerId":1,"space":{"posX":2,"posY":0,"worker":{"sex":"FEMALE","playerId":1,"space":{"posX":2,"posY":0,"worker":{"sex":"FEMALE","playerId":1,"space":{"posX":2,"posY":0,"worker":{"sex":"FEMALE","playerId":1,"space":{"posX":2,"posY":0,"worker":{"sex":"FEMALE","playerId":1,"space":{"posX":2,"posY":0,"worker":{"sex":"FEMALE","playerId":1,"space":{"posX":2,"posY":0,"worker":{"sex":"FEMALE","playerId":1,"space":{"posX":2,"posY":0,"worker":{"sex":"FEMALE","playerId":1,"space":{"posX":2,"posY":0,"worker":{"sex":"FEMALE","playerId":1,"space":{"posX":2,"posY":0,"worker":{"sex":"FEMALE","playerId":1,"space":{"posX":2,"posY":0,"worker":{"sex":"FEMALE","playerId":1,"space":{"posX":2,"posY":0,"worker":{"sex":"FEMALE","playerId":1,"space":{"posX":2,"posY":0,"worker":{"sex":"FEMALE","playerId":1,"space":{"posX":2,"posY":0,"worker":{"sex":"FEMALE","playerId":1,"space":{"posX":2,"posY":0,"worker":{"sex":"FEMALE","playerId":1,"space":{"posX":2,"posY":0,"worker":{"sex":"FEMALE","playerId":1,"space":{"posX":2,"posY":0,"worker":{"sex":"FEMALE","playerId":1,"space":{"posX":2,"posY":0,"worker":{"sex":"FEMALE","playerId":1,"space":{"posX":2,"posY":0,"worker":{"sex":"FEMALE","playerId":1,"space":{"posX":2,"posY":0,"worker":{"sex":"FEMALE","playerId":1,"space":{"posX":2,"posY":0,"worker":{"sex":"FEMALE","playerId":1,"space":{"posX":2,"posY":0,"worker":{"sex":"FEMALE","playerId":1,"space":{"posX":2,"posY":0,"worker":{"sex":"FEMALE","playerId":1,"space":{"posX":2,"posY":0,"worker":{"sex":"FEMALE","playerId":1,"space":{"posX":2,"posY":0,"worker":{"sex":"FEMALE","playerId":1,"space":{"posX":2,"posY":0,"worker":{"sex":"FEMALE","playerId":1,"space":{"posX":2,"posY":0,"worker":{"sex":"FEMALE","playerId":1,"space":{"posX":2,"posY":0,"worker":{"sex":"FEMALE","playerId":1,"space":{"posX":2,"posY":0,"worker":{"sex":"FEMALE","playerId":1,"space":{"posX":2,"posY":0,"worker":{"sex":"FEMALE","playerId":1,"space":{"posX":2,"posY":0,"worker":{"sex":"FEMALE","playerId":1,"space":{"posX":2,"posY":0,"worker":{"sex":"FEMALE","playerId":1,"space":{"posX":2,"posY":0,"worker":{"sex":"FEMALE","playerId":1,"space":{"posX":2,"posY":0,"worker":{"sex":"FEMALE","playerId":1,"space":{"posX":2,"posY":0,"worker":{"sex":"FEMALE","playerId":1,"space":{"posX":2,"posY":0,"worker":{"sex":"FEMALE","playerId":1,"space":{"posX":2,"posY":0,"worker":{"sex":"FEMALE","playerId":1,"space":{"posX":2,"posY":0,"worker":{"sex":"FEMALE","playerId":1,"space":{"posX":2,"posY":0,"worker":{"sex":"FEMALE","playerId":1,"space":{"posX":2,"posY":0,"worker":{"sex":"FEMALE","playerId":1,"space":{"posX":2,"posY":0,"worker":{"sex":"FEMALE","playerId":1,"space":{"posX":2,"posY":0,"worker":{"sex":"FEMALE","playerId":1,"space":{"posX":2,"posY":0,"worker":{"sex":"FEMALE","playerId":1,"space":{"posX":2,"posY":0,"worker":{"sex":"FEMALE","playerId":1,"space":{"posX":2,"posY":0,"worker":{"sex":"FEMALE","playerId":1,"space":{"posX":2,"posY":0,"worker":{"sex":"FEMALE","playerId":1,"space":{"posX":2,"posY":0,"worker":{"sex":"FEMALE","playerId":1,"space":{"posX":2,"posY":0,"worker":{"sex":"FEMALE","playerId":1,"space":{"posX":2,"posY":0,"worker":{"sex":"FEMALE","playerId":1,"space":{"posX":2,"posY":0,"worker":{"sex":"FEMALE","playerId":1,"space":{"posX":2,"posY":0,"worker":{"sex":"FEMALE","playerId":1,"space":{"posX":2,"posY":0,"worker":{"sex":"FEMALE","playerId":1,"space":{"posX":2,"posY":0,"worker":{"sex":"FEMALE","playerId":1,"space":{"posX":2,"posY":0,"worker":{"sex":"FEMALE","playerId":1,"space":{"posX":2,"posY":0,"worker":{"sex":"FEMALE","playerId":1,"space":{"posX":2,"posY":0,"worker":{"sex":"FEMALE","playerId":1,"space":{"posX":2,"posY":0,"worker":{"sex":"FEMALE","playerId":1,"space":{"posX":2,"posY":0,"worker":{"sex":"FEMALE","playerId":1,"space":{"posX":2,"posY":0,"worker":{"sex":"FEMALE","playerId":1,"space":{"posX":2,"posY":0,"worker":{"sex":"FEMALE","playerId":1,"space":{"posX":2,"posY":0,"worker":{"sex":"FEMALE","playerId":1,"space":{"posX":2,"posY":0,"worker":{"sex":"FEMALE","playerId":1,"space":{"posX":2,"posY":0,"worker":{"sex":"FEMALE","playerId":1,"space":{"posX":2,"posY":0,"worker":{"sex":"FEMALE","playerId":1,"space":{"posX":2,"posY":0,"worker":{"sex":"FEMALE","playerId":1,"space":{"posX":2,"posY":0,"worker":{"sex":"FEMALE","playerId":1,"space":{"posX":2,"posY":0,"worker":{"sex":"FEMALE","playerId":1,"space":{"posX":2,"posY":0,"worker":{"sex":"FEMALE","playerId":1,"space":{"posX":2,"posY":0,"worker":{"sex":"FEMALE","playerId":1,"space":{"posX":2,"posY":0,"worker":{"sex":"FEMALE","playerId":1,"space":{"posX":2,"posY":0,"worker":{"sex":"FEMALE","playerId":1,"space":{"posX":2,"posY":0,"worker":{"sex":"FEMALE","playerId":1,"space":{"posX":2,"posY":0,"worker":{"sex":"FEMALE","playerId":1,"space":{"posX":2,"posY":0,"worker":{"sex":"FEMALE","playerId":1,"space":{"posX":2,"posY":0,"worker":{"sex":"FEMALE","playerId":1,"space":{"posX":2,"posY":0,"worker":{"sex":"FEMALE","playerId":1,"space":{"posX":2,"posY":0,"worker":{"sex":"FEMALE","playerId":1,"space":{"posX":2,"posY":0,"worker":{"sex":"FEMALE","playerId":1,"space":{"posX":2,"posY":0,"worker":{"sex":"FEMALE","playerId":1,"space":{"posX":2,"posY":0,"worker":{"sex":"FEMALE","playerId":1,"space":{"posX":2,"posY":0,"worker":{"sex":"FEMALE","playerId":1,"space":{"posX":2,"posY":0,"worker":{"sex":"FEMALE","playerId":1,"space":{"posX":2,"posY":0,"worker":{"sex":"FEMALE","playerId":1,"space":{"posX":2,"posY":0,"worker":{"sex":"FEMALE","playerId":1,"space":{"posX":2,"posY":0,"worker":{"sex":"FEMALE","playerId":1,"space":{"posX":2,"posY":0,"worker":{"sex":"FEMALE","playerId":1,"space":{"posX":2,"posY":0,"worker":{"sex":"FEMALE","playerId":1,"space":{"posX":2,"posY":0,"worker":{"sex":"FEMALE","playerId":1,"space":{"posX":2,"posY":0,"worker":{"sex":"FEMALE","playerId":1,"space":{"posX":2,"posY":0,"worker":{"sex":"FEMALE","playerId":1,"space":{"posX":2,"posY":0,"worker":{"sex":"FEMALE","playerId":1,"space":{"posX":2,"posY":0,"worker":{"sex":"FEMALE","playerId":1,"space":{"posX":2,"posY":0,"worker":{"sex":"FEMALE","playerId":1,"space":{"posX":2,"posY":0,"worker":{"sex":"FEMALE","playerId":1,"space":{"posX":2,"posY":0,"worker":{"sex":"FEMALE","playerId":1,"space":{"posX":2,"posY":0,"worker":{"sex":"FEMALE","playerId":1,"space":{"posX":2,"posY":0,"worker":{"sex":"FEMALE","playerId":1,"space":{"posX":2,"posY":0,"worker":{"sex":"FEMALE","playerId":1,"space":{"posX":2,"posY":0,"worker":{"sex":"FEMALE","playerId":1,"space":{"posX":2,"posY":0,"worker":{"sex":"FEMALE","playerId":1,"space":{"posX":2,"posY":0,"worker":{"sex":"FEMALE","playerId":1,"space":{"posX":2,"posY":0,"worker":{"sex":"FEMALE","playerId":1,"space":{"posX":2,"posY":0,"worker":{"sex":"FEMALE","playerId":1,"space":{"posX":2,"posY":0,"worker":{"sex":"FEMALE","playerId":1,"space":{"posX":2,"posY":0,"worker":{"sex":"FEMALE","playerId":1,"space":{"posX":2,"posY":0,"worker":{"sex":"FEMALE","playerId":1,"space":{"posX":2,"posY":0,"worker":{"sex":"FEMALE","playerId":1,"space":{"posX":2,"posY":0,"worker":{"sex":"FEMALE","playerId":1,"space":{"posX":2,"posY":0,"worker":{"sex":"FEMALE","playerId":1,"space":{"posX":2,"posY":0,"worker":{"sex":"FEMALE","playerId":1,"space":{"posX":2,"posY":0,"worker":{"sex":"FEMALE","playerId":1,"space":{"posX":2,"posY":0,"worker":{"sex":"FEMALE","playerId":1,"space":{"posX":2,"posY":0,"worker":{"sex":"FEMALE","playerId":1,"space":{"posX":2,"posY":0,"worker":{"sex":"FEMALE","playerId":1,"space":{"posX":2,"posY":0,"worker":{"sex":"FEMALE","playerId":1,"space":{"posX":2,"posY":0,"worker":{"sex":"FEMALE","playerId":1,"space":{"posX":2,"posY":0,"worker":{"sex":"FEMALE","playerId":1,"space":{"posX":2,"posY":0,"worker":{"sex":"FEMALE","playerId":1,"space":{"posX":2,"posY":0,"worker":{"sex":"FEMALE","playerId":1,"space":{"posX":2,"posY":0,"worker":{"sex":"FEMALE","playerId":1,"space":{"posX":2,"posY":0,"worker":{"sex":"FEMALE","playerId":1,"space":{"posX":2,"posY":0,"worker":{"sex":"FEMALE","playerId":1,"space":{"posX":2,"posY":0,"worker":{"sex":"FEMALE","playerId":1,"space":{"posX":2,"posY":0,"worker":{"sex":"FEMALE","playerId":1,"space":{"posX":2,"posY":0,"worker":{"sex":"FEMALE","playerId":1,"space":{"posX":2,"posY":0,"worker":{"sex":"FEMALE","playerId":1,"space":{"posX":2,"posY":0,"worker":{"sex":"FEMALE","playerId":1,"space":{"posX":2,"posY":0,"worker":{"sex":"FEMALE","playerId":1,"space":{"posX":2,"posY":0,"worker":{"sex":"FEMALE","playerId":1,"space":{"posX":2,"posY":0,"worker":{"sex":"FEMALE","playerId":1,"space":{"posX":2,"posY":0,"worker":{"sex":"FEMALE","playerId":1,"space":{"posX":2,"posY":0,"worker":{"sex":"FEMALE","playerId":1,"space":{"posX":2,"posY":0,"worker":{"sex":"FEMALE","playerId":1,"space":{"posX":2,"posY":0,"worker":{"sex":"FEMALE","playerId":1,"space":{"posX":2,"posY":0,"worker":{"sex":"FEMALE","playerId":1,"space":{"posX":2,"posY":0,"worker":{"sex":"FEMALE","playerId":1,"space":{"posX":2,"posY":0,"worker":{"sex":"FEMALE","playerId":1,"space":{"posX":2,"posY":0,"worker":{"sex":"FEMALE","playerId":1,"space":{"posX":2,"posY":0,"worker":{"sex":"FEMALE","playerId":1,"space":{"posX":2,"posY":0,"worker":{"sex":"FEMALE","playerId":1,"space":{"posX":2,"posY":0,"worker":{"sex":"FEMALE","playerId":1,"space":{"posX":2,"posY":0,"worker":{"sex":"FEMALE","playerId":1,"space":{"posX":2,"posY":0,"worker":{"sex":"FEMALE","playerId":1,"space":{"posX":2,"posY":0,"worker":{"sex":"FEMALE","playerId":1,"space":{"posX":2,"posY":0,"worker":{"sex":"FEMALE","playerId":1,"space":{"posX":2,"posY":0,"worker":{"sex":"FEMALE","playerId":1,"space":{"posX":2,"posY":0,"worker":{"sex":"FEMALE","playerId":1,"space":{"posX":2,"posY":0,"worker":{"sex":"FEMALE","playerId":1,"space":{"posX":2,"posY":0,"worker":{"sex":"FEMALE","playerId":1,"space":{"posX":2,"posY":0,"worker":{"sex":"FEMALE","playerId":1,"space":{"posX":2,"posY":0,"worker":{"sex":"FEMALE","playerId":1,"space":{"posX":2,"posY":0,"worker":{"sex":"FEMALE","playerId":1,"space":{"posX":2,"posY":0,"worker":{"sex":"FEMALE","playerId":1,"space":{"posX":2,"posY":0,"worker":{"sex":"FEMALE","playerId":1,"space":{"posX":2,"posY":0,"worker":{"sex":"FEMALE","playerId":1,"space":{"posX":2,"posY":0,"worker":{"sex":"FEMALE","playerId":1,"space":{"posX":2,"posY":0,"worker":{"sex":"FEMALE","playerId":1,"space":{"posX":2,"posY":0,"worker":{"sex":"FEMALE","playerId":1,"space":{"posX":2,"posY":0,"worker":{"sex":"FEMALE","playerId":1,"space":{"posX":2,"posY":0,"worker":{"sex":"FEMALE","playerId":1,"space":{"posX":2,"posY":0,"worker":{"sex":"FEMALE","playerId":1,"space":{"posX":2,"posY":0,"worker":{"sex":"FEMALE","playerId":1,"space":{"posX":2,"posY":0,"worker":{"sex":"FEMALE","playerId":1,"space":{"posX":2,"posY":0,"worker":{"sex":"FEMALE","playerId":1,"space":{"posX":2,"posY":0,"worker":{"sex":"FEMALE","playerId":1,"space":{"posX":2,"posY":0,"worker":{"sex":"FEMALE","playerId":1,"space":{"posX":2,"posY":0,"worker":{"sex":"FEMALE","playerId":1,"space":{"posX":2,"posY":0,"worker":{"sex":"FEMALE","playerId":1,"space":{"posX":2,"posY":0,"worker":{"sex":"FEMALE","playerId":1,"space":{"posX":2,"posY":0,"worker":{"sex":"FEMALE","playerId":1,"space":{"posX":2,"posY":0,"worker":{"sex":"FEMALE","playerId":1,"space":{"posX":2,"posY":0,"worker":{"sex":"FEMALE","playerId":1,"space":{"posX":2,"posY":0,"worker":{"sex":"FEMALE","playerId":1,"space":{"posX":2,"posY":0,"worker":{"sex":"FEMALE","playerId":1,"space":{"posX":2,"posY":0,"worker":{"sex":"FEMALE","playerId":1,"space":{"posX":2,"posY":0,"worker":{"sex":"FEMALE","playerId":1,"space":{"posX":2,"posY":0,"worker":{"sex":"FEMALE","playerId":1,"space":{"posX":2,"posY":0,"worker":{"sex":"FEMALE","playerId":1,"space":{"posX":2,"posY":0,"worker":{"sex":"FEMALE","playerId":1,"space":{"posX":2,"posY":0,"worker":{"sex":"FEMALE","playerId":1,"space":{"posX":2,"posY":0,"worker":{"sex":"FEMALE","playerId":1,"space":{"posX":2,"posY":0,"worker":{"sex":"FEMALE","playerId":1,"space":{"posX":2,"posY":0,"worker":{"sex":"FEMALE","playerId":1,"space":{"posX":2,"posY":0,"worker":{"sex":"FEMALE","playerId":1,"space":{"posX":2,"posY":0,"worker":{"sex":"FEMALE","playerId":1,"space":{"posX":2,"posY":0,"worker":{"sex":"FEMALE","playerId":1,"space":{"posX":2,"posY":0,"worker":{"sex":"FEMALE","playerId":1,"space":{"posX":2,"posY":0,"worker":{"sex":"FEMALE","playerId":1,"space":{"posX":2,"posY":0,"worker":{"sex":"FEMALE","playerId":1,"space":{"posX":2,"posY":0,"worker":{"sex":"FEMALE","playerId":1,"space":{"posX":2,"posY":0,"worker":{"sex":"FEMALE","playerId":1,"space":{"posX":2,"posY":0,"worker":{"sex":"FEMALE","playerId":1,"space":{"posX":2,"posY":0,"worker":{"sex":"FEMALE","playerId":1,"space":{"posX":2,"posY":0,"worker":{"sex":"FEMALE","playerId":1,"space":{"posX":2,"posY":0,"worker":{"sex":"FEMALE","playerId":1,"space":{"posX":2,"posY":0,"worker":{"sex":"FEMALE","playerId":1,"space":{"posX":2,"posY":0,"worker":{"sex":"FEMALE","playerId":1,"space":{"posX":2,"posY":0,"worker":{"sex":"FEMALE","playerId":1,"space":{"posX":2,"posY":0,"worker":{"sex":"FEMALE","playerId":1,"space":{"posX":2,"posY":0,"worker":{"sex":"FEMALE","playerId":1,"space":{"posX":2,"posY":0,"worker":{"sex":"FEMALE","playerId":1,"space":{"posX":2,"posY":0,"worker":{"sex":"FEMALE","playerId":1,"space":{"posX":2,"posY":0,"worker":{"sex":"FEMALE","playerId":1,"space":{"posX":2,"posY":0,"worker":{"sex":"FEMALE","playerId":1,"space":{"posX":2,"posY":0,"worker":{"sex":"FEMALE","playerId":1,"space":{"posX":2,"posY":0,"worker":{"sex":"FEMALE","playerId":1,"space":{"posX":2,"posY":0,"worker":{"sex":"FEMALE","playerId":1,"space":{"posX":2,"posY":0,"worker":{"sex":"FEMALE","playerId":1,"space":{"posX":2,"posY":0,"worker":{"sex":"FEMALE","playerId":1,"space":{"posX":2,"posY":0,"worker":{"sex":"FEMALE","playerId":1,"space":{"posX":2,"posY":0,"worker":{"sex":"FEMALE","playerId":1,"space":{"posX":2,"posY":0,"worker":{"sex":"FEMALE","playerId":1,"space":{"posX":2,"posY":0,"worker":{"sex":"FEMALE","playerId":1,"space":{"posX":2,"posY":0,"worker":{"sex":"FEMALE","playerId":1,"space":{"posX":2,"posY":0,"worker":{"sex":"FEMALE","playerId":1,"space":{"posX":2,"posY":0,"worker":{"sex":"FEMALE","playerId":1,"space":{"posX":2,"posY":0,"worker":{"sex":"FEMALE","playerId":1,"space":{"posX":2,"posY":0,"worker":{"sex":"FEMALE","playerId":1,"space":{"posX":2,"posY":0,"worker":{"sex":"FEMALE","playerId":1,"space":{"posX":2,"posY":0,"worker":{"sex":"FEMALE","playerId":1,"space":{"posX":2,"posY":0,"worker":{"sex":"FEMALE","playerId":1,"space":{"posX":2,"posY":0,"worker":{"sex":"FEMALE","playerId":1,"space":{"posX":2,"posY":0,"worker":{"sex":"FEMALE","playerId":1,"space":{"posX":2,"posY":0,"worker":{"sex":"FEMALE","playerId":1,"space":{"posX":2,"posY":0,"worker":{"sex":"FEMALE","playerId":1,"space":{"posX":2,"posY":0,"worker":{"sex":"FEMALE","playerId":1,"space":{"posX":2,"posY":0,"worker":{"sex":"FEMALE","playerId":1,"space":{"posX":2,"posY":0,"worker":{"sex":"FEMALE","playerId":1,"space":{"posX":2,"posY":0,"worker":{"sex":"FEMALE","playerId":1,"space":{"posX":2,"posY":0,"worker":{"sex":"FEMALE","playerId":1,"space":{"posX":2,"posY":0,"worker":{"sex":"FEMALE","playerId":1,"space":{"posX":2,"posY":0,"worker":{"sex":"FEMALE","playerId":1,"space":{"posX":2,"posY":0,"worker":{"sex":"FEMALE","playerId":1,"space":{"posX":2,"posY":0,"worker":{"sex":"FEMALE","playerId":1,"space":{"posX":2,"posY":0,"worker":{"sex":"FEMALE","playerId":1,"space":{"posX":2,"posY":0,"worker":{"sex":"FEMALE","playerId":1,"space":{"posX":2,"posY":0,"worker":{"sex":"FEMALE","playerId":1,"space":{"posX":2,"posY":0,"worker":{"sex":"FEMALE","playerId":1,"space":{"posX":2,"posY":0,"worker":{"sex":"FEMALE","playerId":1,"space":{"posX":2,"posY":0,"worker":{"sex":"FEMALE","playerId":1,"space":{"posX":2,"posY":0,"worker":{"sex":"FEMALE","playerId":1,"space":{"posX":2,"posY":0,"worker":{"sex":"FEMALE","playerId":1,"space":{"posX":2,"posY":0,"worker":{"sex":"FEMALE","playerId":1,"space":{"posX":2,"posY":0,"worker":{"sex":"FEMALE","playerId":1,"space":{"posX":2,"posY":0,"worker":{"sex":"FEMALE","playerId":1,"space":{"posX":2,"posY":0,"worker":{"sex":"FEMALE","playerId":1,"space":{"posX":2,"posY":0,"worker":{"sex":"FEMALE","playerId":1,"space":{"posX":2,"posY":0,"worker":{"sex":"FEMALE","playerId":1,"space":{"posX":2,"posY":0,"worker":{"sex":"FEMALE","playerId":1,"space":{"posX":2,"posY":0,"worker":{"sex":"FEMALE","playerId":1,"space":{"posX":2,"posY":0,"worker":{"sex":"FEMALE","playerId":1,"space":{"posX":2,"posY":0,"worker":{"sex":"FEMALE","playerId":1,"space":{"posX":2,"posY":0,"worker":{"sex":"FEMALE","playerId":1,"space":{"posX":2,"posY":0,"worker":{"sex":"FEMALE","playerId":1,"space":{"posX":2,"posY":0,"worker":{"sex":"FEMALE","playerId":1,"space":{"posX":2,"posY":0,"worker":{"sex":"FEMALE","playerId":1,"space":{"posX":2,"posY":0,"worker":{"sex":"FEMALE","playerId":1,"space":{"posX":2,"posY":0,"worker":{"sex":"FEMALE","playerId":1,"space":{"posX":2,"posY":0,"worker":{"sex":"FEMALE","playerId":1,"space":{"posX":2,"posY":0,"worker":{"sex":"FEMALE","playerId":1,"space":{"posX":2,"posY":0,"worker":{"sex":"FEMALE","playerId":1,"space":{"posX":2,"posY":0,"worker":{"sex":"FEMALE","playerId":1,"space":{"posX":2,"posY":0,"worker":{"sex":"FEMALE","playerId":1,"space":{"posX":2,"posY":0,"worker":{"sex":"FEMALE","playerId":1,"space":{"posX":2,"posY":0,"worker":{"sex":"FEMALE","playerId":1,"space":{"posX":2,"posY":0,"worker":{"sex":"FEMALE","playerId":1,"space":{"posX":2,"posY":0,"worker":{"sex":"FEMALE","playerId":1,"space":{"posX":2,"posY":0,"worker":{"sex":"FEMALE","playerId":1,"space":{"posX":2,"posY":0,"worker":{"sex":"FEMALE","playerId":1,"space":{"posX":2,"posY":0,"worker":{"sex":"FEMALE","playerId":1,"space":{"posX":2,"posY":0,"worker":{"sex":"FEMALE","playerId":1,"space":{"posX":2,"posY":0,"worker":{"sex":"FEMALE","playerId":1,"space":{"posX":2,"posY":0,"worker":{"sex":"FEMALE","playerId":1,"space":{"posX":2,"posY":0,"worker":{"sex":"FEMALE","playerId":1,"space":{"posX":2,"posY":0,"worker":{"sex":"FEMALE","playerId":1,"space":{"posX":2,"posY":0,"worker":{"sex":"FEMALE","playerId":1,"space":{"posX":2,"posY":0,"worker":{"sex":"FEMALE","playerId":1,"space":{"posX":2,"posY":0,"worker":{"sex":"FEMALE","playerId":1,"space":{"posX":2,"posY":0,"worker":{"sex":"FEMALE","playerId":1,"space":{"posX":2,"posY":0,"worker":{"sex":"FEMALE","playerId":1,"space":{"posX":2,"posY":0,"worker":{"sex":"FEMALE","playerId":1,"space":{"posX":2,"posY":0,"worker":{"sex":"FEMALE","playerId":1,"space":{"posX":2,"posY":0,"worker":{"sex":"FEMALE","playerId":1,"space":{"posX":2,"posY":0,"worker":{"sex":"FEMALE","playerId":1,"space":{"posX":2,"posY":0,"worker":{"sex":"FEMALE","playerId":1,"space":{"posX":2,"posY":0,"worker":{"sex":"FEMALE","playerId":1,"space":{"posX":2,"posY":0,"worker":{"sex":"FEMALE","playerId":1,"space":{"posX":2,"posY":0,"worker":{"sex":"FEMALE","playerId":1,"space":{"posX":2,"posY":0,"worker":{"sex":"FEMALE","playerId":1,"space":{"posX":2,"posY":0,"worker":{"sex":"FEMALE","playerId":1,"space":{"posX":2,"posY":0,"worker":{"sex":"FEMALE","playerId":1,"space":{"posX":2,"posY":0,"worker":{"sex":"FEMALE","playerId":1,"space":{"posX":2,"posY":0,"worker":{"sex":"FEMALE","playerId":1,"space":{"posX":2,"posY":0,"worker":{"sex":"FEMALE","playerId":1,"space":{"posX":2,"posY":0,"worker":{"sex":"FEMALE","playerId":1,"space":{"posX":2,"posY":0,"worker":{"sex":"FEMALE","playerId":1,"space":{"posX":2,"posY":0,"worker":{"sex":"FEMALE","playerId":1,"space":{"posX":2,"posY":0,"worker":{"sex":"FEMALE","playerId":1,"space":{"posX":2,"posY":0,"worker":{"sex":"FEMALE","playerId":1,"space":{"posX":2,"posY":0,"worker":{"sex":"FEMALE","playerId":1,"space":{"posX":2,"posY":0,"worker":{"sex":"FEMALE","playerId":1,"space":{"posX":2,"posY":0,"worker":{"sex":"FEMALE","playerId":1,"space":{"posX":2,"posY":0,"worker":{"sex":"FEMALE","playerId":1,"space":{"posX":2,"posY":0,"worker":{"sex":"FEMALE","playerId":1,"space":{"posX":2,"posY":0,"worker":{"sex":"FEMALE","playerId":1,"space":{"posX":2,"posY":0,"worker":{"sex":"FEMALE","playerId":1,"space":{"posX":2,"posY":0,"worker":{"sex":"FEMALE","playerId":1,"space":{"posX":2,"posY":0,"worker":{"sex":"FEMALE","playerId":1,"space":{"posX":2,"posY":0,"worker":{"sex":"FEMALE","playerId":1,"space":{"posX":2,"posY":0,"worker":{"sex":"FEMALE","playerId":1,"space":{"posX":2,"posY":0,"worker":{"sex":"FEMALE","playerId":1,"space":{"posX":2,"posY":0,"worker":{"sex":"FEMALE","playerId":1,"space":{"posX":2,"posY":0,"worker":{"sex":"FEMALE","playerId":1,"space":{"posX":2,"posY":0,"worker":{"sex":"FEMALE","playerId":1,"space":{"posX":2,"posY":0,"worker":{"sex":"FEMALE","playerId":1,"space":{"posX":2,"posY":0,"worker":{"sex":"FEMALE","playerId":1,"space":{"posX":2,"posY":0,"worker":{"sex":"FEMALE","playerId":1,"space":{"posX":2,"posY":0,"worker":{"sex":"FEMALE","playerId":1,"space":{"posX":2,"posY":0,"worker":{"sex":"FEMALE","playerId":1,"space":{"posX":2,"posY":0,"worker":{"sex":"FEMALE","playerId":1,"space":{"posX":2,"posY":0,"worker":{"sex":"FEMALE","playerId":1,"space":{"posX":2,"posY":0,"worker":{"sex":"FEMALE","playerId":1,"space":{"posX":2,"posY":0,"worker":{"sex":"FEMALE","playerId":1,"space":{"posX":2,"posY":0,"worker":{"sex":"FEMALE","playerId":1,"space":{"posX":2,"posY":0,"worker":{"sex":"FEMALE","playerId":1,"space":{"posX":2,"posY":0,"worker":{"sex":"FEMALE","playerId":1,"space":{"posX":2,"posY":0,"worker":{"sex":"FEMALE","playerId":1,"space":{"posX":2,"posY":0,"worker":{"sex":"FEMALE","playerId":1,"space":{"posX":2,"posY":0,"worker":{"sex":"FEMALE","playerId":1,"space":{"posX":2,"posY":0,"worker":{"sex":"FEMALE","playerId":1,"space":{"posX":2,"posY":0,"worker":{"sex":"FEMALE","playerId":1,"space":{"posX":2,"posY":0,"worker":{"sex":"FEMALE","playerId":1,"space":{"posX":2,"posY":0,"worker":{"sex":"FEMALE","playerId":1,"space":{"posX":2,"posY":0,"worker":{"sex":"FEMALE","playerId":1,"space":{"posX":2,"posY":0,"worker":{"sex":"FEMALE","playerId":1,"space":{"posX":2,"posY":0,"worker":{"sex":"FEMALE","playerId":1,"space":{"posX":2,"posY":0,"worker":{"sex":"FEMALE","playerId":1,"space":{"posX":2,"posY":0,"worker":{"sex":"FEMALE","playerId":1,"space":{"posX":2,"posY":0,"worker":{"sex":"FEMALE","playerId":1,"space":{"posX":2,"posY":0,"worker":{"sex":"FEMALE","playerId":1,"space":{"posX":2,"posY":0,"worker":{"sex":"FEMALE","playerId":1,"space":{"posX":2,"posY":0,"worker":{"sex":"FEMALE","playerId":1,"space":{"posX":2,"posY":0,"worker":{"sex":"FEMALE","playerId":1,"space":{"posX":2,"posY":0,"worker":{"sex":"FEMALE","playerId":1,"space":{"posX":2,"posY":0,"worker":{"sex":"FEMALE","playerId":1,"space":{"posX":2,"posY":0,"worker":{"sex":"FEMALE","playerId":1,"space":{"posX":2,"posY":0,"worker":{"sex":"FEMALE","playerId":1,"space":{"posX":2,"posY":0,"worker":{"sex":"FEMALE","playerId":1,"space":{"posX":2,"posY":0,"worker":{"sex":"FEMALE","playerId":1,"space":{"posX":2,"posY":0,"worker":{"sex":"FEMALE","playerId":1,"space":{"posX":2,"posY":0,"worker":{"sex":"FEMALE","playerId":1,"space":{"posX":2,"posY":0,"worker":{"sex":"FEMALE","playerId":1,"space":{"posX":2,"posY":0,"worker":{"sex":"FEMALE","playerId":1,"space":{"posX":2,"posY":0,"worker":{"sex":"FEMALE","playerId":1,"space":{"posX":2,"posY":0,"worker":{"sex":"FEMALE","playerId":1,"space":{"posX":2,"posY":0,"worker":{"sex":"FEMALE","playerId":1,"space":{"posX":2,"posY":0,"worker":{"sex":"FEMALE","playerId":1,"space":{"posX":2,"posY":0,"worker":{"sex":"FEMALE","playerId":1,"space":{"posX":2,"posY":0,"worker":{"sex":"FEMALE","playerId":1,"space":{"posX":2,"posY":0,"worker":{"sex":"FEMALE","playerId":1,"space":{"posX":2,"posY":0,"worker":{"sex":"FEMALE","playerId":1,"space":{"posX":2,"posY":0,"worker":{"sex":"FEMALE","playerId":1,"space":{"posX":2,"posY":0,"worker":{"sex":"FEMALE","playerId":1,"space":{"posX":2,"posY":0,"worker":{"sex":"FEMALE","playerId":1,"space":{"posX":2,"posY":0,"worker":{"sex":"FEMALE","playerId":1,"space":{"posX":2,"posY":0,"worker":{"sex":"FEMALE","playerId":1,"space":{"posX":2,"posY":0,"worker":{"sex":"FEMALE","playerId":1,"space":{"posX":2,"posY":0,"worker":{"sex":"FEMALE","playerId":1,"space":{"posX":2,"posY":0,"worker":{"sex":"FEMALE","playerId":1,"space":{"posX":2,"posY":0,"worker":{"sex":"FEMALE","playerId":1,"space":{"posX":2,"posY":0,"worker":{"sex":"FEMALE","playerId":1,"space":{"posX":2,"posY":0,"worker":{"sex":"FEMALE","playerId":1,"space":{"posX":2,"posY":0,"worker":{"sex":"FEMALE","playerId":1,"space":{"posX":2,"posY":0,"worker":{"sex":"FEMALE","playerId":1,"space":{"posX":2,"posY":0,"worker":{"sex":"FEMALE","playerId":1,"space":{"posX":2,"posY":0,"worker":{"sex":"FEMALE","playerId":1,"space":{"posX":2,"posY":0,"worker":{"sex":"FEMALE","playerId":1,"space":{"posX":2,"posY":0,"worker":{"sex":"FEMALE","playerId":1,"space":{"posX":2,"posY":0,"worker":{"sex":"FEMALE","playerId":1,"space":{"posX":2,"posY":0,"worker":{"sex":"FEMALE","playerId":1,"space":{"posX":2,"posY":0,"worker":{"sex":"FEMALE","playerId":1,"space":{"posX":2,"posY":0,"worker":{"sex":"FEMALE","playerId":1,"space":{"posX":2,"posY":0,"worker":{"sex":"FEMALE","playerId":1,"space":{"posX":2,"posY":0,"worker":{"sex":"FEMALE","playerId":1,"space":{"posX":2,"posY":0,"worker":{"sex":"FEMALE","playerId":1,"space":{"posX":2,"posY":0,"worker":{"sex":"FEMALE","playerId":1,"space":{"posX":2,"posY":0,"worker":{"sex":"FEMALE","playerId":1,"space":{"posX":2,"posY":0,"worker":{"sex":"FEMALE","playerId":1,"space":{"posX":2,"posY":0,"worker":{"sex":"FEMALE","playerId":1,"space":{"posX":2,"posY":0,"worker":{"sex":"FEMALE","playerId":1,"space":{"posX":2,"posY":0,"worker":{"sex":"FEMALE","playerId":1,"space":{"posX":2,"posY":0,"worker":{"sex":"FEMALE","playerId":1,"space":{"posX":2,"posY":0,"worker":{"sex":"FEMALE","playerId":1,"space":{"posX":2,"posY":0,"worker":{"sex":"FEMALE","playerId":1,"space":{"posX":2,"posY":0,"worker":{"sex":"FEMALE","playerId":1,"space":{"posX":2,"posY":0,"worker":{"sex":"FEMALE","playerId":1,"space":{"posX":2,"posY":0,"worker":{"sex":"FEMALE","playerId":1,"space":{"posX":2,"posY":0,"worker":{"sex":"FEMALE","playerId":1,"space":{"posX":2,"posY":0,"worker":{"sex":"FEMALE","playerId":1,"space":{"posX":2,"posY":0,"worker":{"sex":"FEMALE","playerId":1,"space":{"posX":2,"posY":0,"worker":{"sex":"FEMALE","playerId":1,"space":{"posX":2,"posY":0,"worker":{"sex":"FEMALE","playerId":1,"space":{"posX":2,"posY":0,"worker":{"sex":"FEMALE","playerId":1,"space":{"posX":2,"posY":0,"worker":{"sex":"FEMALE","playerId":1,"space":{"posX":2,"posY":0,"worker":{"sex":"FEMALE","playerId":1,"space":{"posX":2,"posY":0,"worker":{"sex":"FEMALE","playerId":1,"space":{"posX":2,"posY":0,"worker":{"sex":"FEMALE","playerId":1,"space":{"posX":2,"posY":0,"worker":{"sex":"FEMALE","playerId":1,"space":{"posX":2,"posY":0,"worker":{"sex":"FEMALE","playerId":1,"space":{"posX":2,"posY":0,"worker":{"sex":"FEMALE","playerId":1,"space":{"posX":2,"posY":0,"worker":{"sex":"FEMALE","playerId":1,"space":{"posX":2,"posY":0,"worker":{"sex":"FEMALE","playerId":1,"space":{"posX":2,"posY":0,"worker":{"sex":"FEMALE","playerId":1,"space":{"posX":2,"posY":0,"worker":{"sex":"FEMALE","playerId":1,"space":{"posX":2,"posY":0,"worker":{"sex":"FEMALE","playerId":1,"space":{"posX":2,"posY":0,"worker":{"sex":"FEMALE","playerId":1,"space":{"posX":2,"posY":0,"worker":{"sex":"FEMALE","playerId":1,"space":{"posX":2,"posY":0,"worker":{"sex":"FEMALE","playerId":1,"space":{"posX":2,"posY":0,"worker":{"sex":"FEMALE","playerId":1,"space":{"posX":2,"posY":0,"worker":{"sex":"FEMALE","playerId":1,"space":{"posX":2,"posY":0,"worker":{"sex":"FEMALE","playerId":1,"space":{"posX":2,"posY":0,"worker":{"sex":"FEMALE","playerId":1,"space":{"posX":2,"posY":0,"worker":{"sex":"FEMALE","playerId":1,"space":{"posX":2,"posY":0,"worker":{"sex":"FEMALE","playerId":1,"space":{"posX":2,"posY":0,"worker":{"sex":"FEMALE","playerId":1,"space":{"posX":2,"posY":0,"worker":{"sex":"FEMALE","playerId":1,"space":{"posX":2,"posY":0,"worker":{"sex":"FEMALE","playerId":1,"space":{"posX":2,"posY":0,"worker":{"sex":"FEMALE","playerId":1,"space":{"posX":2,"posY":0,"worker":{"sex":"FEMALE","playerId":1,"space":{"posX":2,"posY":0,"worker":{"sex":"FEMALE","playerId":1,"space":{"posX":2,"posY":0,"worker":{"sex":"FEMALE","playerId":1,"space":{"posX":2,"posY":0,"worker":{"sex":"FEMALE","playerId":1,"space":{"posX":2,"posY":0,"worker":{"sex":"FEMALE","playerId":1,"space":{"posX":2,"posY":0,"worker":{"sex":"FEMALE","playerId":1,"space":{"posX":2,"posY":0,"worker":{"sex":"FEMALE","playerId":1,"space":{"posX":2,"posY":0,"worker":{"sex":"FEMALE","playerId":1,"space":{"posX":2,"posY":0,"worker":{"sex":"FEMALE","playerId":1,"space":{"posX":2,"posY":0,"worker":{"sex":"FEMALE","playerId":1,"space":{"posX":2,"posY":0,"worker":{"sex":"FEMALE","playerId":1,"space":{"posX":2,"posY":0,"worker":{"sex":"FEMALE","playerId":1,"space":{"posX":2,"posY":0,"worker":{"sex":"FEMALE","playerId":1,"space":{"posX":2,"posY":0,"worker":{"sex":"FEMALE","playerId":1,"space":{"posX":2,"posY":0,"worker":{"sex":"FEMALE","playerId":1,"space":{"posX":2,"posY":0,"worker":{"sex":"FEMALE","playerId":1,"space":{"posX":2,"posY":0,"worker":{"sex":"FEMALE","playerId":1,"space":{"posX":2,"posY":0,"worker":{"sex":"FEMALE","playerId":1,"space":{"posX":2,"posY":0,"worker":{"sex":"FEMALE","playerId":1,"space":{"posX":2,"posY":0,"worker":{"sex":"FEMALE","playerId":1,"space":{"posX":2,"posY":0,"worker":{"sex":"FEMALE","playerId":1,"space":{"posX":2,"posY":0,"worker":{"sex":"FEMALE","playerId":1,"space":{"posX":2,"posY":0,"worker":{"sex":"FEMALE","playerId":1,"space":{"posX":2,"posY":0,"worker":{"sex":"FEMALE","playerId":1,"space":{"posX":2,"posY":0,"worker":{"sex":"FEMALE","playerId":1,"space":{"posX":2,"posY":0,"worker":{"sex":"FEMALE","playerId":1,"space":{"posX":2,"posY":0,"worker":{"sex":"FEMALE","playerId":1,"space":{"posX":2,"posY":0,"worker":{"sex":"FEMALE","playerId":1,"space":{"posX":2,"posY":0,"worker":{"sex":"FEMALE","playerId":1,"space":{"posX":2,"posY":0,"worker":{"sex":"FEMALE","playerId":1,"space":{"posX":2,"posY":0,"worker":{"sex":"FEMALE","playerId":1,"space":{"posX":2,"posY":0,"worker":{"sex":"FEMALE","playerId":1,"space":{"posX":2,"posY":0,"worker":{"sex":"FEMALE","playerId":1,"space":{"posX":2,"posY":0,"worker":{"sex":"FEMALE","playerId":1,"space":{"posX":2,"posY":0,"worker":{"sex":"FEMALE","playerId":1,"space":{"posX":2,"posY":0,"worker":{"sex":"FEMALE","playerId":1,"space":{"posX":2,"posY":0,"worker":{"sex":"FEMALE","playerId":1,"space":{"posX":2,"posY":0,"worker":{"sex":"FEMALE","playerId":1,"space":{"posX":2,"posY":0,"worker":{"sex":"FEMALE","playerId":1,"space":{"posX":2,"posY":0,"worker":{"sex":"FEMALE","playerId":1,"space":{"posX":2,"posY":0,"worker":{"sex":"FEMALE","playerId":1,"space":{"posX":2,"posY":0,"worker":{"sex":"FEMALE","playerId":1,"space":{"posX":2,"posY":0,"worker":{"sex":"FEMALE","playerId":1,"space":{"posX":2,"posY":0,"worker":{"sex":"FEMALE","playerId":1,"space":{"posX":2,"posY":0,"worker":{"sex":"FEMALE","playerId":1,"space":{"posX":2,"posY":0,"worker":{"sex":"FEMALE","playerId":1,"space":{"posX":2,"posY":0,"worker":{"sex":"FEMALE","playerId":1,"space":{"posX":2,"posY":0,"worker":{"sex":"FEMALE","playerId":1,"space":{"posX":2,"posY":0,"worker":{"sex":"FEMALE","playerId":1,"space":{"posX":2,"posY":0,"worker":{"sex":"FEMALE","playerId":1,"space":{"posX":2,"posY":0,"worker":{"sex":"FEMALE","playerId":1,"space":{"posX":2,"posY":0,"worker":{"sex":"FEMALE","playerId":1,"space":{"posX":2,"posY":0,"worker":{"sex":"FEMALE","playerId":1,"space":{"posX":2,"posY":0,"worker":{"sex":"FEMALE","playerId":1,"space":{"posX":2,"posY":0,"worker":{"sex":"FEMALE","playerId":1,"space":{"posX":2,"posY":0,"worker":{"sex":"FEMALE","playerId":1,"space":{"posX":2,"posY":0,"worker":{"sex":"FEMALE","playerId":1,"space":{"posX":2,"posY":0,"worker":{"sex":"FEMALE","playerId":1,"space":{"posX":2,"posY":0,"worker":{"sex":"FEMALE","playerId":1,"space":{"posX":2,"posY":0,"worker":{"sex":"FEMALE","playerId":1,"space":{"posX":2,"posY":0,"worker":{"sex":"FEMALE","playerId":1,"space":{"posX":2,"posY":0,"worker":{"sex":"FEMALE","playerId":1,"space":{"posX":2,"posY":0,"worker":{"sex":"FEMALE","playerId":1,"space":{"posX":2,"posY":0,"worker":{"sex":"FEMALE","playerId":1,"space":{"posX":2,"posY":0,"worker":{"sex":"FEMALE","playerId":1,"space":{"posX":2,"posY":0,"worker":{"sex":"FEMALE","playerId":1,"space":{"posX":2,"posY":0,"worker":{"sex":"FEMALE","playerId":1,"space":{"posX":2,"posY":0,"worker":{"sex":"FEMALE","playerId":1,"space":{"posX":2,"posY":0,"worker":{"sex":"FEMALE","playerId":1,"space":{"posX":2,"posY":0,"worker":{"sex":"FEMALE","playerId":1,"space":{"posX":2,"posY":0,"worker":{"sex":"FEMALE","playerId":1,"space":{"posX":2,"posY":0,"worker":{"sex":"FEMALE","playerId":1,"space":{"posX":2,"posY":0,"worker":{"sex":"FEMALE","playerId":1,"space":{"posX":2,"posY":0,"worker":{"sex":"FEMALE","playerId":1,"space":{"posX":2,"posY":0,"worker":{"sex":"FEMALE","playerId":1,"space":{"posX":2,"posY":0,"worker":{"sex":"FEMALE","playerId":1,"space":{"posX":2,"posY":0,"worker":{"sex":"FEMALE","playerId":1,"space":{"posX":2,"posY":0,"worker":{"sex":"FEMALE","playerId":1,"space":{"posX":2,"posY":0,"worker":{"sex":"FEMALE","playerId":1,"space":{"posX":2,"posY":0,"worker":{"sex":"FEMALE","playerId":1,"space":{"posX":2,"posY":0,"worker":{"sex":"FEMALE","playerId":1,"space":{"posX":2,"posY":0,"worker":{"sex":"FEMALE","playerId":1,"space":{"posX":2,"posY":0,"worker":{"sex":"FEMALE","playerId":1,"space":{"posX":2,"posY":0,"worker":{"sex":"FEMALE","playerId":1,"space":{"posX":2,"posY":0,"worker":{"sex":"FEMALE","playerId":1,"space":{"posX":2,"posY":0,"worker":{"sex":"FEMALE","playerId":1,"space":{"posX":2,"posY":0,"worker":{"sex":"FEMALE","playerId":1,"space":{"posX":2,"posY":0,"worker":{"sex":"FEMALE","playerId":1,"space":{"posX":2,"posY":0,"worker":{"sex":"FEMALE","playerId":1,"space":{"posX":2,"posY":0,"worker":{"sex":"FEMALE","playerId":1,"space":{"posX":2,"posY":0,"worker":{"sex":"FEMALE","playerId":1,"space":{"posX":2,"posY":0,"worker":{"sex":"FEMALE","playerId":1,"space":{"posX":2,"posY":0,"worker":{"sex":"FEMALE","playerId":1,"space":{"posX":2,"posY":0,"worker":{"sex":"FEMALE","playerId":1,"space":{"posX":2,"posY":0,"worker":{"sex":"FEMALE","playerId":1,"space":{"posX":2,"posY":0,"worker":{"sex":"FEMALE","playerId":1,"space":{"posX":2,"posY":0,"worker":{"sex":"FEMALE","playerId":1,"space":{"posX":2,"posY":0,"worker":{"sex":"FEMALE","playerId":1,"space":{"posX":2,"posY":0,"worker":{"sex":"FEMALE","playerId":1,"space":{"posX":2,"posY":0,"worker":{"sex":"FEMALE","playerId":1,"space":{"posX":2,"posY":0,"worker":{"sex":"FEMALE","playerId":1,"space":{"posX":2,"posY":0,"worker":{"sex":"FEMALE","playerId":1,"space":{"posX":2,"posY":0,"worker":{"sex":"FEMALE","playerId":1,"space":{"posX":2,"posY":0,"worker":{"sex":"FEMALE","playerId":1,"space":{"posX":2,"posY":0,"worker":{"sex":"FEMALE","playerId":1,"space":{"posX":2,"posY":0,"worker":{"sex":"FEMALE","playerId":1,"space":{"posX":2,"posY":0,"worker":{"sex":"FEMALE","playerId":1,"space":{"posX":2,"posY":0,"worker":{"sex":"FEMALE","playerId":1,"space":{"posX":2,"posY":0,"worker":{"sex":"FEMALE","playerId":1,"space":{"posX":2,"posY":0,"worker":{"sex":"FEMALE","playerId":1,"space":{"posX":2,"posY":0,"worker":{"sex":"FEMALE","playerId":1,"space":{"posX":2,"posY":0,"worker":{"sex":"FEMALE","playerId":1,"space":{"posX":2,"posY":0,"worker":{"sex":"FEMALE","playerId":1,"space":{"posX":2,"posY":0,"worker":{"sex":"FEMALE","playerId":1,"space":{"posX":2,"posY":0,"worker":{"sex":"FEMALE","playerId":1,"space":{"posX":2,"posY":0,"worker":{"sex":"FEMALE","playerId":1,"space":{"posX":2,"posY":0,"worker":{"sex":"FEMALE","playerId":1,"space":{"posX":2,"posY":0,"worker":{"sex":"FEMALE","playerId":1,"space":{"posX":2,"posY":0,"worker":{"sex":"FEMALE","playerId":1,"space":{"posX":2,"posY":0,"worker":{"sex":"FEMALE","playerId":1,"space":{"posX":2,"posY":0,"worker":{"sex":"FEMALE","playerId":1,"space":{"posX":2,"posY":0,"worker":{"sex":"FEMALE","playerId":1,"space":{"posX":2,"posY":0,"worker":{"sex":"FEMALE","playerId":1,"space":{"posX":2,"posY":0,"worker":{"sex":"FEMALE","playerId":1,"space":{"posX":2,"posY":0,"worker":{"sex":"FEMALE","playerId":1,"space":{"posX":2,"posY":0,"worker":{"sex":"FEMALE","playerId":1,"space":{"posX":2,"posY":0,"worker":{"sex":"FEMALE","playerId":1,"space":{"posX":2,"posY":0,"worker":{"sex":"FEMALE","playerId":1,"space":{"posX":2,"posY":0,"worker":{"sex":"FEMALE","playerId":1,"space":{"posX":2,"posY":0,"worker":{"sex":"FEMALE","playerId":1,"space":{"posX":2,"posY":0,"worker":{"sex":"FEMALE","playerId":1,"space":{"posX":2,"posY":0,"worker":{"sex":"FEMALE","playerId":1,"space":{"posX":2,"posY":0,"worker":{"sex":"FEMALE","playerId":1,"space":{"posX":2,"posY":0,"worker":{"sex":"FEMALE","playerId":1,"space":{"posX":2,"posY":0,"worker":{"sex":"FEMALE","playerId":1,"space":{"posX":2,"posY":0,"worker":{"sex":"FEMALE","playerId":1,"space":{"posX":2,"posY":0,"worker":{"sex":"FEMALE","playerId":1,"space":{"posX":2,"posY":0,"worker":{"sex":"FEMALE","playerId":1,"space":{"posX":2,"posY":0,"worker":{"sex":"FEMALE","playerId":1,"space":{"posX":2,"pos